setup.py
sqlite_db_tools/__init__.py
sqlite_db_tools/common.py
sqlite_db_tools/migrate.py
sqlite_db_tools.egg-info/PKG-INFO
sqlite_db_tools.egg-info/SOURCES.txt
sqlite_db_tools.egg-info/dependency_links.txt
sqlite_db_tools.egg-info/not-zip-safe
sqlite_db_tools.egg-info/top_level.txt