Metadata-Version: 1.0
Name: sqlite-db-tools
Version: 0.1
Summary: Tools for managing sqlite3 databases.
Home-page: https://github.com/Adam_Davenport/sqlite_db_tools
Author: Adam Davenport
Author-email: UNKNOWN
License: MIT
Platform: UNKNOWN
